ppromptor/__init__.py
ppromptor/agent.py
ppromptor/config.py
ppromptor/db.py
ppromptor/utils.py
ppromptor/analyzers/__init__.py
ppromptor/base/__init__.py
ppromptor/base/command.py
ppromptor/base/schemas.py
ppromptor/evaluators/__init__.py
ppromptor/job_queues/__init__.py
ppromptor/llms/__init__.py
ppromptor/llms/wizardlm.py
ppromptor/loggers/__init__.py
ppromptor/proposers/__init__.py
ppromptor/scorefuncs/__init__.py
ppromptor-0.1.4.data/scripts/ppromptor-cli.py
ppromptor-0.1.4.dist-info/LICENSE
ppromptor-0.1.4.dist-info/METADATA
ppromptor-0.1.4.dist-info/WHEEL
ppromptor-0.1.4.dist-info/top_level.txt
ppromptor-0.1.4.dist-info/RECORD
